{
"type": "FeatureCollection",
"name": "tern-points-down",
"crs": { "type": "name", "properties": { "name": "urn:ogc:def:crs:OGC:1.3:CRS84" } },
"features": [
{ "type": "Feature", "properties": { "timestamp": "2017-09-16 23:46:00", "long": -82.08530769, "lat": -17.6703344, "end_timest": "2017-09-17 10:59:00", "lat_lower": -32.54977089, "lat_upper": 5.32693381, "long_lower": -89.23911293, "long_upper": -75.83293925, "start_time": "2017-09-16 23:46:00", "sensor_typ": "solar-geolocator", "individual": "Sterna paradisaea", "tag_ident": "BF372", "ind_ident": "1342-16798", "study_name": "MCP Arctic Tern North America", "date": null, "time": null }, "geometry": { "type": "Point", "coordinates": [ -82.08530769, -17.6703344 ] } }

]
}
